mosaik_components/mango/__init__.py
mosaik_components/mango/simulator.py
mosaik_mango-0.2.1.dist-info/METADATA
mosaik_mango-0.2.1.dist-info/WHEEL
mosaik_mango-0.2.1.dist-info/licenses/LICENSE
mosaik_mango-0.2.1.dist-info/RECORD
