Metadata-Version: 2.3
Name: mosaik-mango
Version: 0.2.1
Summary: An adapter to integrate a mango simulation into mosaik
Author-email: Eike Schulte <eike.schulte@offis.de>
License-Expression: MIT
License-File: LICENSE
Requires-Python: >=3.9
Requires-Dist: loguru~=0.6
Requires-Dist: mango-agents~=1.1.3
Requires-Dist: mosaik-api-v3~=3.0.4
